wakapy/__init__.py
wakapy/containers.py
wakapy/day.py
wakapy/exceptions.py
wakapy/parser.py
wakapy/plot.py
wakapy/user.py
wakapy/utils.py
wakapy-0.0.1.dist-info/LICENSE.md
wakapy-0.0.1.dist-info/METADATA
wakapy-0.0.1.dist-info/WHEEL
wakapy-0.0.1.dist-info/top_level.txt
wakapy-0.0.1.dist-info/RECORD
