Metadata-Version: 2.1
Name: wakapy
Version: 0.0.1
Summary: Wakatime data manipulation
Home-page: https://github.com/surister/wakapy
Author: surister
Author-email: surister98@gmail.com
License: UNKNOWN
Platform: UNKNOWN
Classifier: Programming Language :: Python :: 3
Classifier: License :: OSI Approved :: MIT License
Classifier: Topic :: Internet
Classifier: Topic :: Utilities
Requires-Python: >3.6.0
Requires-Dist: matplotlib
